coininfo_ivan/__init__.py
coininfo_ivan/human.py
coininfo_ivan/info.py
tests/__init__.py
tests/test_project.py
coininfo_ivan-0.5.dist-info/METADATA
coininfo_ivan-0.5.dist-info/WHEEL
coininfo_ivan-0.5.dist-info/top_level.txt
coininfo_ivan-0.5.dist-info/RECORD
