Metadata-Version: 2.1
Name: coininfo-ivan
Version: 0.5
Requires-Dist: requests ==2.31.0
